{
  "name": "LAG.barberia - Panel de Administración",
  "short_name": "Admin LAG",
  "description": "Panel de control para administrar LAG.barberia",
  "start_url": "/LAG-barberia/admin-login.html",
  "scope": "/LAG-barberia/",
  "display": "standalone",
  "background_color": "#1a1a1a",
  "theme_color": "#c49b63",
  "orientation": "portrait",
  "categories": ["business", "productivity"],
  "icons": [
    {
      "src": "/LAG-barberia/icons/admin-icon-72x72.png",
      "sizes": "72x72",
      "type": "image/png",
      "purpose": "any maskable"
    },
    {
      "src": "/LAG-barberia/icons/admin-icon-96x96.png",
      "sizes": "96x96",
      "type": "image/png",
      "purpose": "any maskable"
    },
    {
      "src": "/LAG-barberia/icons/admin-icon-128x128.png",
      "sizes": "128x128",
      "type": "image/png",
      "purpose": "any maskable"
    },
    {
      "src": "/LAG-barberia/icons/admin-icon-144x144.png",
      "sizes": "144x144",
      "type": "image/png",
      "purpose": "any maskable"
    },
    {
      "src": "/LAG-barberia/icons/admin-icon-152x152.png",
      "sizes": "152x152",
      "type": "image/png",
      "purpose": "any maskable"
    },
    {
      "src": "/LAG-barberia/icons/admin-icon-192x192.png",
      "sizes": "192x192",
      "type": "image/png",
      "purpose": "any maskable"
    },
    {
      "src": "/LAG-barberia/icons/admin-icon-384x384.png",
      "sizes": "384x384",
      "type": "image/png",
      "purpose": "any maskable"
    },
    {
      "src": "/LAG-barberia/icons/admin-icon-512x512.png",
      "sizes": "512x512",
      "type": "image/png",
      "purpose": "any maskable"
    }
  ]
}